smear_api/__init__.py
smear_api/tools.py
smear_api_tools-0.3.0.dist-info/LICENSE.txt
smear_api_tools-0.3.0.dist-info/METADATA
smear_api_tools-0.3.0.dist-info/WHEEL
smear_api_tools-0.3.0.dist-info/top_level.txt
smear_api_tools-0.3.0.dist-info/RECORD
