Metadata-Version: 2.1
Name: smear-api-tools
Version: 0.3.0
Summary: Utility functions for using the SmartSMEAR API
Home-page: https://github.com/jlpl/smear-api-tools
Author: Janne Lampilahti
Author-email: janne.lampilahti@helsinki.fi
License-File: LICENSE.txt
Requires-Dist: pandas >=1.0.0
Requires-Dist: numpy >=1.19.0
Provides-Extra: dev
Requires-Dist: pytest >=3.6 ; extra == 'dev'
